organize/__init__.py
processing/__init__.py
ProcessingImg1-0.3.dist-info/LICENSE.txt
ProcessingImg1-0.3.dist-info/METADATA
ProcessingImg1-0.3.dist-info/WHEEL
ProcessingImg1-0.3.dist-info/top_level.txt
ProcessingImg1-0.3.dist-info/RECORD
